coordsystems/__init__.py
coordsystems/main.py
coordsystems/py.typed
coordsystems-0.0.3.dist-info/METADATA
coordsystems-0.0.3.dist-info/WHEEL
coordsystems-0.0.3.dist-info/entry_points.txt
coordsystems-0.0.3.dist-info/licenses/LICENSE
coordsystems-0.0.3.dist-info/RECORD
