Metadata-Version: 2.4
Name: coordsystems
Version: 0.0.3
Summary: A package for dealing with different coordinate reference system.
Author-email: Heliton Martins <helitonmrf@gmail.com>
License-File: LICENSE
Classifier: Operating System :: OS Independent
Classifier: Programming Language :: Python :: 3
Requires-Python: >=3.9
Requires-Dist: numpy>1.24.4
Requires-Dist: plum-dispatch
